nameless/__init__.py
nameless/__main__.py
nameless-1.0.0.dist-info/RECORD
nameless-1.0.0.dist-info/top_level.txt
nameless-1.0.0.dist-info/DESCRIPTION.rst
nameless-1.0.0.dist-info/METADATA
nameless-1.0.0.dist-info/metadata.json
nameless-1.0.0.dist-info/entry_points.txt
nameless-1.0.0.dist-info/WHEEL
